django_uwsgi/__init__.py
django_uwsgi/apps.py
django_uwsgi/cache.py
django_uwsgi/compat.py
django_uwsgi/decorators.py
django_uwsgi/mail.py
django_uwsgi/panels.py
django_uwsgi/stats.py
django_uwsgi/tasks.py
django_uwsgi/template.py
django_uwsgi/urls.py
django_uwsgi/views.py
django_uwsgi/wagtail_compat.py
django_uwsgi/wagtail_hooks.py
django_uwsgi/emperor/__init__.py
django_uwsgi/emperor/admin.py
django_uwsgi/emperor/apps.py
django_uwsgi/emperor/models.py
django_uwsgi/emperor/wagtail_hooks.py
django_uwsgi/emperor/migrations/0001_initial.py
django_uwsgi/emperor/migrations/__init__.py
django_uwsgi/management/__init__.py
django_uwsgi/management/commands/__init__.py
django_uwsgi/management/commands/runuwsgi.py
django_uwsgi/templates/uwsgi/panel.html
django_uwsgi/templates/uwsgi/uwsgi.html
django_uwsgi/templates/uwsgi/wagtail_dashboard_item.html
django_uwsgi/templates/uwsgi/wagtail_uwsgi.html
django_uwsgi-0.2.2.dist-info/DESCRIPTION.rst
django_uwsgi-0.2.2.dist-info/METADATA
django_uwsgi-0.2.2.dist-info/RECORD
django_uwsgi-0.2.2.dist-info/WHEEL
django_uwsgi-0.2.2.dist-info/metadata.json
django_uwsgi-0.2.2.dist-info/top_level.txt
